segytools/__init__.py
segytools/datatypes.py
segytools/segy_abstract_header.py
segytools/segy_file_header.py
segytools/segy_header_item.py
segytools/segy_trace_header.py
segytools/toolkit.py
segytools/utils.py
segytools-0.2.3.dist-info/LICENSE
segytools-0.2.3.dist-info/METADATA
segytools-0.2.3.dist-info/WHEEL
segytools-0.2.3.dist-info/RECORD
