Metadata-Version: 2.1
Name: segytools
Version: 0.2.3
Summary: low level toolkit for manipulating and analyzing segy formatted data
License: MIT
Author: anthonytorlucci
Author-email: anthonytorlucci@gmail.com
Requires-Python: >=3.10,<4.0
Classifier: License :: OSI Approved :: MIT License
Classifier: Operating System :: OS Independent
Classifier: Programming Language :: Python :: 3
Classifier: Programming Language :: Python :: 3.10
Classifier: Programming Language :: Python :: 3.11
Requires-Dist: ibm2ieee (>=1.2.0,<2.0.0)
